LICENSE
MANIFEST.in
README.md
setup.py
example_project/mkdocs.yml
example_project/docs/index.md
example_project/docs/story.md
example_project/docs/_includes/fn_function_meta.j2
src/mkdocs_vwmetahelper/__init__.py
src/mkdocs_vwmetahelper/plugin.py
src/mkdocs_vwmetahelper.egg-info/PKG-INFO
src/mkdocs_vwmetahelper.egg-info/SOURCES.txt
src/mkdocs_vwmetahelper.egg-info/dependency_links.txt
src/mkdocs_vwmetahelper.egg-info/entry_points.txt
src/mkdocs_vwmetahelper.egg-info/requires.txt
src/mkdocs_vwmetahelper.egg-info/top_level.txt