Metadata-Version: 2.1
Name: mkdocs-vwmetahelper
Version: 0.1.0
Summary: MkDocs plugin providing get_meta() and call_macro() with lazy front-matter indexing.
Home-page: https://github.com/your-org/mkdocs-vwmetahelper
Author: Che Wei Chang & Contributors
License: MIT
Project-URL: Issues, https://github.com/your-org/mkdocs-vwmetahelper/issues
Platform: UNKNOWN
Classifier: Programming Language :: Python :: 3
Classifier: License :: OSI Approved :: MIT License
Classifier: Operating System :: OS Independent
Classifier: Framework :: MkDocs
Requires-Python: >=3.8
License-File: LICENSE
